{
  "meta": {
    "family": "community-favorite",
    "collection": "community"
  },
  "dark": {
    "--bg": "#1a1b26",
    "--surface": "#1f2335",
    "--card": "#24283b",
    "--card-bg": "#24283b",
    "--card-border": "rgba(122, 162, 247, 0.14)",
    "--text": "#c0caf5",
    "--text-secondary": "#a9b1d6",
    "--muted": "#565f89",
    "--good": "#9ece6a",
    "--warn": "#e0af68",
    "--crit": "#f7768e",
    "--accent": "#7aa2f7",
    "--accent-hover": "#89b4fa",
    "--accent-muted": "rgba(122, 162, 247, 0.14)",
    "--info": "#2ac3de",
    "--input-border": "rgba(122, 162, 247, 0.18)",
    "--overlay": "rgba(15, 18, 30, 0.74)",
    "--hover-bg": "rgba(122, 162, 247, 0.08)",
    "--void": "#16161e",
    "--void-deep": "#101017",
    "--elevated": "#292e42",
    "--hover": "#343b58",
    "--amethyst": "#bb9af7",
    "--amethyst-light": "#c0caf5",
    "--sapphire": "#7dcfff",
    "--success": "#9ece6a",
    "--warning": "#e0af68",
    "--danger": "#f7768e",
    "--text-primary": "#c0caf5",
    "--text-muted": "#565f89",
    "--glass-bg": "rgba(26, 27, 38, 0.86)",
    "--glass-border": "rgba(122, 162, 247, 0.1)"
  },
  "light": {
    "--bg": "#d5d6db",
    "--surface": "#cbccd1",
    "--card": "#ffffff",
    "--card-bg": "#ffffff",
    "--card-border": "rgba(52, 84, 138, 0.14)",
    "--text": "#3760bf",
    "--text-secondary": "#6172b0",
    "--muted": "#848cb5",
    "--good": "#587539",
    "--warn": "#8c6c3e",
    "--crit": "#c64343",
    "--accent": "#34548a",
    "--accent-hover": "#2e4f89",
    "--accent-muted": "rgba(52, 84, 138, 0.1)",
    "--info": "#0f4b6e",
    "--input-border": "rgba(52, 84, 138, 0.14)",
    "--overlay": "rgba(0, 0, 0, 0.3)",
    "--hover-bg": "rgba(52, 84, 138, 0.05)",
    "--void": "#d5d6db",
    "--void-deep": "#cbccd1",
    "--elevated": "#bfc0c5",
    "--hover": "#b3b4b9",
    "--amethyst": "#5a4a78",
    "--amethyst-light": "#7a5ea6",
    "--sapphire": "#34548a",
    "--success": "#587539",
    "--warning": "#8c6c3e",
    "--danger": "#c64343",
    "--text-primary": "#3760bf",
    "--text-muted": "#848cb5",
    "--glass-bg": "rgba(255, 255, 255, 0.8)",
    "--glass-border": "rgba(52, 84, 138, 0.08)"
  }
}
